conforge/__init__.py
conforge/cli.py
conforge/configs.py
conforge/main.py
conforge/utils.py
conforge-2.0.1.dist-info/LICENSE
conforge-2.0.1.dist-info/METADATA
conforge-2.0.1.dist-info/WHEEL
conforge-2.0.1.dist-info/entry_points.txt
conforge-2.0.1.dist-info/RECORD
