Metadata-Version: 2.1
Name: conforge
Version: 2.0.1
Summary: A tool for generating config files from given templates and variables.
License: GPL-3.0-only
Author: ScriptHoodie
Author-email: dev@scripthoodie.dev
Requires-Python: >=3.11,<4.0
Classifier: License :: OSI Approved :: GNU General Public License v3 (GPLv3)
Classifier: Programming Language :: Python :: 3
Classifier: Programming Language :: Python :: 3.11
Requires-Dist: jinja2 (>=3.1.6,<4.0.0)
Requires-Dist: pyyaml (>=6.0.3,<7.0.0)
Project-URL: Homepage, https://codeberg.org/scripthoodie/conforge
Project-URL: Issues, https://codeberg.org/scripthoodie/conforge/issues
